gen3schemadev/__init__.py
gen3schemadev/cli.py
gen3schemadev/converter.py
gen3schemadev/ddvis.py
gen3schemadev/schema/__init__.py
gen3schemadev/schema/gen3_template.py
gen3schemadev/schema/input_schema.py
gen3schemadev/schema/schema_templates/_definitions.yaml
gen3schemadev/schema/schema_templates/_settings.yaml
gen3schemadev/schema/schema_templates/_terms.yaml
gen3schemadev/schema/schema_templates/core_metadata_collection.yaml
gen3schemadev/schema/schema_templates/gen3_metaschema.yml
gen3schemadev/schema/schema_templates/program.yaml
gen3schemadev/schema/schema_templates/project.yaml
gen3schemadev/utils.py
gen3schemadev/validators/input_validator.py
gen3schemadev/validators/metaschema_validator.py
gen3schemadev/validators/rule_validator.py
gen3schemadev-2.3.3.dist-info/METADATA
gen3schemadev-2.3.3.dist-info/WHEEL
gen3schemadev-2.3.3.dist-info/entry_points.txt
gen3schemadev-2.3.3.dist-info/licenses/LICENSE
gen3schemadev-2.3.3.dist-info/RECORD
