Metadata-Version: 2.4
Name: Gen3SchemaDev
Version: 2.3.3
Summary: Tool for data modelling in Gen3
License: Apache 2.0
License-File: LICENSE
Author: JoshuaHarris391
Author-email: harjo391@gmail.com
Requires-Python: >=3.12.10,<4.0
Classifier: License :: Other/Proprietary License
Classifier: Programming Language :: Python :: 3
Classifier: Programming Language :: Python :: 3.13
Classifier: Programming Language :: Python :: 3.14
Requires-Dist: check-jsonschema (>=0.34.1,<0.35.0)
Requires-Dist: gen3-validator (>=1.1.1,<2.0.0)
Requires-Dist: linkml (>=1.9.4,<2.0.0)
Requires-Dist: pydantic (>=2.11.9,<3.0.0)
Requires-Dist: setuptools (>=70.0)
